README.md
setup.py
eway/__init__.py
eway/rapid/__init__.py
eway/rapid/client.py
eway/rapid/endpoint.py
eway/rapid/exception.py
eway/rapid/model.py
eway/rapid/payment_method/__init__.py
eway/rapid/payment_method/transparent_redirect/__init__.py
eway/rapid/payment_method/transparent_redirect/request.py
eway/rapid/payment_method/transparent_redirect/response.py
eway_rapid_python.egg-info/PKG-INFO
eway_rapid_python.egg-info/SOURCES.txt
eway_rapid_python.egg-info/dependency_links.txt
eway_rapid_python.egg-info/requires.txt
eway_rapid_python.egg-info/top_level.txt