Metadata-Version: 1.0
Name: eway-rapid-python
Version: 0.8
Summary: Python client implementation for eWAY Rapid API v3
Home-page: https://github.com/springload/eway-rapid-python
Author: Sergey Latyntsev at Springload
Author-email: dnsl48@gmail.com
License: MIT
Keywords: eway
Platform: UNKNOWN
